gravi_cli/__init__.py
gravi_cli/api.py
gravi_cli/auth.py
gravi_cli/cli.py
gravi_cli/client.py
gravi_cli/config.py
gravi_cli/exceptions.py
gravi_cli/tunnel.py
gravi_cli-0.2.8.dist-info/METADATA
gravi_cli-0.2.8.dist-info/WHEEL
gravi_cli-0.2.8.dist-info/entry_points.txt
gravi_cli-0.2.8.dist-info/licenses/LICENSE
gravi_cli-0.2.8.dist-info/RECORD
