Metadata-Version: 2.4
Name: gravi-cli
Version: 0.2.8
Summary: CLI tool for Gravitate infrastructure management
Project-URL: Homepage, https://github.com/gravitate/mom
Project-URL: Documentation, https://github.com/gravitate/mom/tree/main/cli
Project-URL: Repository, https://github.com/gravitate/mom
Author-email: Gravitate Engineering <engineering@gravitate.com>
License: Proprietary
License-File: LICENSE
Keywords: cli,devops,gravitate,infrastructure
Classifier: Development Status :: 3 - Alpha
Classifier: Intended Audience :: Developers
Classifier: License :: Other/Proprietary License
Classifier: Programming Language :: Python :: 3
Classifier: Programming Language :: Python :: 3.10
Classifier: Programming Language :: Python :: 3.11
Classifier: Programming Language :: Python :: 3.12
Classifier: Programming Language :: Python :: 3.13
Requires-Python: >=3.10
Requires-Dist: click>=8.1.0
Requires-Dist: pydantic>=2.0.0
Requires-Dist: requests>=2.31.0
Requires-Dist: websockets>=10.0
Provides-Extra: test
Requires-Dist: pytest-cov>=4.1.0; extra == 'test'
Requires-Dist: pytest-mock>=3.11.0; extra == 'test'
Requires-Dist: pytest>=7.4.0; extra == 'test'
Requires-Dist: responses>=0.24.0; extra == 'test'
